PyPix/__init__.py
PyPix/scan_pbi.py
PyPix_AndrewP-0.0.1.dist-info/METADATA
PyPix_AndrewP-0.0.1.dist-info/WHEEL
PyPix_AndrewP-0.0.1.dist-info/entry_points.txt
PyPix_AndrewP-0.0.1.dist-info/top_level.txt
PyPix_AndrewP-0.0.1.dist-info/RECORD
