Metadata-Version: 2.1
Name: PyPix-AndrewP
Version: 0.0.1
Summary: Python with PowerBi
Home-page: UNKNOWN
License: UNKNOWN
Platform: UNKNOWN
Classifier: Programming Language :: Python :: 3
Classifier: License :: OSI Approved :: MIT License
Classifier: Operating System :: OS Independent
Requires-Python: >=3.8
